{
  "resourceType": "StructureDefinition",
  "id": "ServiceRequestCabaRecupero",
  "url": "http://recuperocaba.gob.ar/StructureDefinition/ServiceRequestCabaRecupero",
  "name": "ServiceRequestCabaRecupero",
  "title": "ServiceRequest para Recupero CABA",
  "status": "draft",
  "description": "Perfil de ServiceRequest Para RECUPERO CABA",
  "fhirVersion": "4.0.1",
  "kind": "resource",
  "abstract": false,
  "type": "ServiceRequest",
  "baseDefinition": "http://hl7.org/fhir/StructureDefinition/ServiceRequest",
  "derivation": "constraint",
  "differential": {
    "element": [
      {
        "id": "ServiceRequest.identifier",
        "path": "ServiceRequest.identifier",
        "short": "DatosContexto.idPedido",
        "min": 1,
        "max": "1"
      },
      {
        "id": "ServiceRequest.identifier.system",
        "path": "ServiceRequest.identifier.system",
        "min": 1
      },
      {
        "id": "ServiceRequest.identifier.value",
        "path": "ServiceRequest.identifier.value",
        "min": 1
      },
      {
        "id": "ServiceRequest.status",
        "path": "ServiceRequest.status",
        "patternCode": "completed"
      },
      {
        "id": "ServiceRequest.intent",
        "path": "ServiceRequest.intent",
        "patternCode": "order"
      },
      {
        "id": "ServiceRequest.category",
        "path": "ServiceRequest.category",
        "min": 1,
        "max": "1",
        "patternCodeableConcept": {
          "coding": [
            {
              "code": "108252007",
              "system": "http://snomed.info/sct",
              "display": "Laboratory Procedure"
            }
          ]
        }
      },
      {
        "id": "ServiceRequest.subject",
        "path": "ServiceRequest.subject",
        "type": [
          {
            "code": "Reference",
            "targetProfile": [
              "http://recuperocaba.gob.ar/StructureDefinition/PatientCabaRecupero"
            ]
          }
        ]
      },
      {
        "id": "ServiceRequest.encounter",
        "path": "ServiceRequest.encounter",
        "min": 1,
        "type": [
          {
            "code": "Reference",
            "targetProfile": [
              "http://recuperocaba.gob.ar/StructureDefinition/EncounterCabaRecupero"
            ]
          }
        ]
      },
      {
        "id": "ServiceRequest.occurrence[x]",
        "path": "ServiceRequest.occurrence[x]",
        "slicing": {
          "discriminator": [
            {
              "type": "type",
              "path": "$this"
            }
          ],
          "ordered": false,
          "rules": "open"
        },
        "min": 1
      },
      {
        "id": "ServiceRequest.occurrence[x]:occurrenceDateTime",
        "path": "ServiceRequest.occurrence[x]",
        "sliceName": "occurrenceDateTime",
        "short": "fechasServicio.fechaResultado",
        "min": 1,
        "max": "1",
        "type": [
          {
            "code": "dateTime"
          }
        ]
      },
      {
        "id": "ServiceRequest.authoredOn",
        "path": "ServiceRequest.authoredOn",
        "short": "fechasServicio.fechaMuestra",
        "min": 1
      },
      {
        "id": "ServiceRequest.requester",
        "path": "ServiceRequest.requester",
        "short": "ProfesionalSolicitante",
        "min": 1,
        "type": [
          {
            "code": "Reference",
            "targetProfile": [
              "http://recuperocaba.gob.ar/StructureDefinition/PractitionerCabaRecupero"
            ]
          }
        ]
      },
      {
        "id": "ServiceRequest.performer",
        "path": "ServiceRequest.performer",
        "short": "ProfesionalFirmante",
        "min": 1,
        "max": "1",
        "type": [
          {
            "code": "Reference",
            "targetProfile": [
              "http://recuperocaba.gob.ar/StructureDefinition/PractitionerCabaRecupero"
            ]
          }
        ]
      },
      {
        "id": "ServiceRequest.locationCode",
        "path": "ServiceRequest.locationCode",
        "min": 1,
        "max": "1"
      },
      {
        "id": "ServiceRequest.locationCode.text",
        "path": "ServiceRequest.locationCode.text",
        "short": "DatosContexto.desAreaJerarquicaSolicitud",
        "min": 1
      }
    ]
  }
}
